odoo/addons/account_move_line_residual/README.rst
odoo/addons/account_move_line_residual/__init__.py
odoo/addons/account_move_line_residual/__manifest__.py
odoo/addons/account_move_line_residual/i18n/account_move_line_residual.pot
odoo/addons/account_move_line_residual/i18n/es.po
odoo/addons/account_move_line_residual/readme/CONTRIBUTORS.rst
odoo/addons/account_move_line_residual/readme/DESCRIPTION.rst
odoo/addons/account_move_line_residual/readme/USAGE.rst
odoo/addons/account_move_line_residual/static/description/icon.png
odoo/addons/account_move_line_residual/static/description/index.html
odoo/addons/account_move_line_residual/views/account_move_line_view.xml
odoo_addon_account_move_line_residual-15.0.1.0.1.2.dist-info/METADATA
odoo_addon_account_move_line_residual-15.0.1.0.1.2.dist-info/WHEEL
odoo_addon_account_move_line_residual-15.0.1.0.1.2.dist-info/top_level.txt
odoo_addon_account_move_line_residual-15.0.1.0.1.2.dist-info/RECORD
